LICENSE
README.md
chi_io.py
pyblowfish.py
setup.py
chi_io.egg-info/PKG-INFO
chi_io.egg-info/SOURCES.txt
chi_io.egg-info/dependency_links.txt
chi_io.egg-info/top_level.txt