Metadata-Version: 2.1
Name: chi_io
Version: 1.0.1
Summary: Pure Python read/write encryption/decryption of encrypted Tombo chi files 
Home-page: https://github.com/clach04/chi_io
Author: clach04
Platform: any
Classifier: Development Status :: 4 - Beta
Classifier: License :: OSI Approved :: Apache Software License
Classifier: Operating System :: OS Independent
Classifier: Programming Language :: Python
Classifier: Programming Language :: Python :: 2
Classifier: Programming Language :: Python :: 3
Classifier: Programming Language :: Python :: 3.5
License-File: LICENSE
